azure/communication/chat/__init__.py
azure/communication/chat/_chat_client.py
azure/communication/chat/_chat_thread_client.py
azure/communication/chat/_communication_identifier_serializer.py
azure/communication/chat/_models.py
azure/communication/chat/_utils.py
azure/communication/chat/_version.py
azure/communication/chat/py.typed
azure/communication/chat/_common/__init__.py
azure/communication/chat/_generated/__init__.py
azure/communication/chat/_generated/_azure_communication_chat_service.py
azure/communication/chat/_generated/_configuration.py
azure/communication/chat/_generated/_patch.py
azure/communication/chat/_generated/_serialization.py
azure/communication/chat/_generated/_vendor.py
azure/communication/chat/_generated/py.typed
azure/communication/chat/_generated/aio/__init__.py
azure/communication/chat/_generated/aio/_azure_communication_chat_service.py
azure/communication/chat/_generated/aio/_configuration.py
azure/communication/chat/_generated/aio/_patch.py
azure/communication/chat/_generated/aio/operations/__init__.py
azure/communication/chat/_generated/aio/operations/_chat_operations.py
azure/communication/chat/_generated/aio/operations/_chat_thread_operations.py
azure/communication/chat/_generated/aio/operations/_patch.py
azure/communication/chat/_generated/models/__init__.py
azure/communication/chat/_generated/models/_azure_communication_chat_service_enums.py
azure/communication/chat/_generated/models/_models_py3.py
azure/communication/chat/_generated/models/_patch.py
azure/communication/chat/_generated/operations/__init__.py
azure/communication/chat/_generated/operations/_chat_operations.py
azure/communication/chat/_generated/operations/_chat_thread_operations.py
azure/communication/chat/_generated/operations/_patch.py
azure/communication/chat/_shared/__init__.py
azure/communication/chat/_shared/auth_policy_utils.py
azure/communication/chat/_shared/models.py
azure/communication/chat/_shared/policy.py
azure_communication_chat-1.3.0.dist-info/LICENSE
azure_communication_chat-1.3.0.dist-info/METADATA
azure_communication_chat-1.3.0.dist-info/WHEEL
azure_communication_chat-1.3.0.dist-info/top_level.txt
azure_communication_chat-1.3.0.dist-info/RECORD
